tricli/__init__.py
tricli/__main__.py
tricli-2.1.9.dist-info/LICENSE
tricli-2.1.9.dist-info/METADATA
tricli-2.1.9.dist-info/WHEEL
tricli-2.1.9.dist-info/entry_points.txt
tricli-2.1.9.dist-info/top_level.txt
tricli-2.1.9.dist-info/RECORD
