Metadata-Version: 2.1
Name: tricli
Version: 2.1.9
Summary: tricli manages a trie data structure that can be globally accessed.
Home-page: UNKNOWN
Author: Anish Lakkapragada
Author-email: anish.lakkapragada@gmail.com
License: MIT
Keywords: REST,Data Structures,Trie
Platform: UNKNOWN
